{"metadata":{"formatVersion":{"major":0,"minor":6,"patch":0},"generator":"Apple Swift version 6.2.3 (swiftlang-6.2.3.3.21 clang-1700.6.3.2)"},"module":{"name":"ARHelloFace","platform":{"architecture":"arm64","vendor":"apple","operatingSystem":{"name":"ios","minimumVersion":{"major":16,"minor":0}}}},"symbols":[{"kind":{"identifier":"swift.enum","displayName":"Enumeration"},"identifier":{"precise":"s:11ARHelloFaceAAO","interfaceLanguage":"swift"},"pathComponents":["ARHelloFace"],"names":{"title":"ARHelloFace","navigator":[{"kind":"identifier","spelling":"ARHelloFace"}],"subHeading":[{"kind":"keyword","spelling":"enum"},{"kind":"text","spelling":" "},{"kind":"identifier","spelling":"ARHelloFace"}]},"docComment":{"uri":"file:///Users/leeminji/Downloads/ARHelloFace/Sources/ARHelloFace/ARHelloFace.swift","module":"ARHelloFace","lines":[{"range":{"start":{"line":4,"character":4},"end":{"line":4,"character":91}},"text":"ARKit Face Tracking으로 얼굴 위에 \"Hello\" 텍스트를 표시하는 튜토리얼."},{"range":{"start":{"line":5,"character":3},"end":{"line":5,"character":3}},"text":""},{"range":{"start":{"line":6,"character":4},"end":{"line":6,"character":32}},"text":"## 튜토리얼 시작하기"},{"range":{"start":{"line":7,"character":3},"end":{"line":7,"character":3}},"text":""},{"range":{"start":{"line":8,"character":4},"end":{"line":8,"character":87}},"text":"이 패키지에는 ARKit의 Face Tracking 기능을 단계별로 배울 수 있는"},{"range":{"start":{"line":9,"character":4},"end":{"line":9,"character":51}},"text":"DocC 튜토리얼이 포함되어 있습니다."},{"range":{"start":{"line":10,"character":3},"end":{"line":10,"character":3}},"text":""},{"range":{"start":{"line":11,"character":4},"end":{"line":11,"character":88}},"text":"`Product > Build Documentation` (⌃⇧⌘D) 으로 튜토리얼을 빌드하세요."}]},"declarationFragments":[{"kind":"keyword","spelling":"enum"},{"kind":"text","spelling":" "},{"kind":"identifier","spelling":"ARHelloFace"}],"accessLevel":"public","location":{"uri":"file:///Users/leeminji/Downloads/ARHelloFace/Sources/ARHelloFace/ARHelloFace.swift","position":{"line":12,"character":12}}}],"relationships":[]}